ai4gcnpy/__init__.py
ai4gcnpy/agents.py
ai4gcnpy/chains.py
ai4gcnpy/cli.py
ai4gcnpy/core.py
ai4gcnpy/db_client.py
ai4gcnpy/llm_client.py
ai4gcnpy/py.typed
ai4gcnpy/utils.py
ai4gcnpy-0.1.1.dist-info/METADATA
ai4gcnpy-0.1.1.dist-info/WHEEL
ai4gcnpy-0.1.1.dist-info/entry_points.txt
ai4gcnpy-0.1.1.dist-info/licenses/LICENSE
ai4gcnpy-0.1.1.dist-info/RECORD
