Metadata-Version: 2.4
Name: ai4gcnpy
Version: 0.1.1
Summary: A Graph Database Toolkit for NASA's GCN
Project-URL: Repository, https://github.com/GZU-MuTian/AI4GCNpy
Author-email: yuliu <yuliu@gzu.edu.cn>
License: MIT
License-File: LICENSE
Requires-Python: >=3.12
Requires-Dist: aiofiles>=25.1.0
Requires-Dist: jinja2>=3.1.6
Requires-Dist: langchain-community>=0.4.1
Requires-Dist: langchain-deepseek>=1.0.1
Requires-Dist: langchain-ollama>=1.0.0
Requires-Dist: langchain-openai>=1.0.3
Requires-Dist: langchain>=1.0.8
Requires-Dist: langgraph>=1.0.3
Requires-Dist: neo4j-graphrag
Requires-Dist: neo4j~=5.19.0
Requires-Dist: pandas>=2.3.3
Requires-Dist: rich>=14.2.0
Requires-Dist: typer>=0.20.0
